data_memory.v
module data_mem(
    input wire        clk,
    input wire        mem_read,
    input wire        mem_write,

    input wire [2:0]  funct3,
    input wire [31:0] address,
    input wire [31:0] write_data,
    output reg [31:0] read_data
);

reg [7:0] memory [0:4095];  // 4KB byte-addressable memory
wire [11:0] addr = address[11:0];

// Combinational READ (loads)

always @(*) begin
    if (mem_read) begin
        case (funct3)
            3'b000: read_data = {{24{memory[addr][7]}}, memory[addr]};                       // LB
            3'b001: read_data = {{16{memory[addr+1][7]}}, memory[addr+1], memory[addr]};     // LH
            3'b010: read_data = {memory[addr+3], memory[addr+2], memory[addr+1], memory[addr]}; // LW
            3'b100: read_data = {24'd0, memory[addr]};                                      // LBU
            3'b101: read_data = {16'd0, memory[addr+1], memory[addr]};                      // LHU
            default: read_data = 32'd0;
        endcase
    end else begin
        read_data = 32'd0;
    end
end


// Sequential WRITE (stores)

always @(posedge clk) begin
    if (mem_write) begin
        case (funct3)
            3'b000: memory[addr] <= write_data[7:0];                           // SB
            3'b001: begin                                                     // SH
                memory[addr]     <= write_data[7:0];
                memory[addr + 1] <= write_data[15:8];
            end
            3'b010: begin                                                     // SW
                memory[addr]     <= write_data[7:0];
                memory[addr + 1] <= write_data[15:8];
                memory[addr + 2] <= write_data[23:16];
                memory[addr + 3] <= write_data[31:24];
            end
        endcase
    end
end

endmodule

Single Pipelined/branch_unit.v
module branch_unit(
    input wire branch,
    input wire [31:0] rs1,
    input wire [31:0] rs2,
    input wire [2:0] funct3,
    output reg branch_taken
);
always @(*) begin
    if (!branch) begin
        branch_taken = 0;
    end 
    else begin
        case (funct3)
            3'b000: branch_taken = (rs1 == rs2);          // BEQ
            3'b001: branch_taken = (rs1 != rs2);          // BNE
            3'b100: branch_taken = ($signed(rs1) < $signed(rs2)); // BLT
            3'b101: branch_taken = ($signed(rs1) >= $signed(rs2)); // BGE
            3'b110: branch_taken = (rs1 < rs2);           // BLTU
            3'b111: branch_taken = (rs1 >= rs2);          // BGEU
            default: branch_taken = 0;
        endcase
    end
end

endmodule

Single Pipelined/alu.v
module ALU(
    input wire [31:0] a,
    input wire [31:0] b,
    input wire [3:0]  alu_op,
    output reg [31:0] result,
    output reg zero 
);

    always @(*) begin
        case (alu_op)
            4'b0000: result = a + b;                         // ADD
            4'b0001: result = a - b;                         // SUB
            4'b0010: result = a & b;                         // AND
            4'b0011: result = a | b;                         // OR
            4'b0100: result = a ^ b;                         // XOR

            4'b0101: result = ($signed(a) < $signed(b))      // SLT (signed)
                             ? 32'd1 : 32'd0;

            4'b0110: result = (a < b)                        // SLTU (unsigned)
                             ? 32'd1 : 32'd0;

            4'b0111: result = a << b[4:0];                   // SLL
            4'b1000: result = a >> b[4:0];                   // SRL
            4'b1001: result = $signed(a) >>> b[4:0];         // SRA

            default: result = 32'd0;
        endcase

        zero = (result == 32'd0);
    end

endmodule

control_unit.v
module control_unit(
    input  [6:0] opcode,
    input  [2:0] funct3,
    input  [6:0] funct7,

    output reg [3:0] alu_op,
    output reg alu_src,
    output reg mem_to_reg,
    output reg reg_write,
    output reg mem_read,
    output reg mem_write,
    output reg branch,
    output reg jal,
    output reg jalr
);

always @(*) begin

    // Default control signals
    alu_src     = 0;
    mem_to_reg  = 0;
    reg_write   = 0;
    mem_read    = 0;
    mem_write   = 0;
    branch      = 0;
    jal         = 0;
    jalr        = 0;
    alu_op      = 4'b0000; // ADD

    case (opcode)

        // ---------------------------
        // R-Type
        // ---------------------------
        7'b0110011: begin
            reg_write = 1;
            alu_src   = 0;

            case ({funct7,funct3})
                10'b0000000_000: alu_op = 4'b0000; // ADD
                10'b0100000_000: alu_op = 4'b0001; // SUB
                10'b0000000_111: alu_op = 4'b0010; // AND
                10'b0000000_110: alu_op = 4'b0011; // OR
                10'b0000000_100: alu_op = 4'b0100; // XOR
                10'b0000000_010: alu_op = 4'b0101; // SLT
                10'b0000000_011: alu_op = 4'b0110; // SLTU
                10'b0000000_001: alu_op = 4'b0111; // SLL
                10'b0000000_101: alu_op = 4'b1000; // SRL
                10'b0100000_101: alu_op = 4'b1001; // SRA
            endcase
        end

        // ---------------------------
        // Load
        // ---------------------------
        7'b0000011: begin
            reg_write  = 1;
            alu_src    = 1;
            mem_read   = 1;
            mem_to_reg = 1;
            alu_op     = 4'b0000; // ADD
        end

        // ---------------------------
        // Store
        // ---------------------------
        7'b0100011: begin
            alu_src   = 1;
            mem_write = 1;
            alu_op    = 4'b0000; // ADD
        end

        // ---------------------------
        // Branch
        // ---------------------------
        7'b1100011: begin
            branch    = 1;
            alu_op    = 4'b0001; // SUB for comparison
        end

        // ---------------------------
        // JAL
        // ---------------------------
        7'b1101111: begin
            reg_write = 1;
            jal       = 1;
        end

        // ---------------------------
        // JALR
        // ---------------------------
        7'b1100111: begin
            reg_write = 1;
            alu_src   = 1;
            jalr      = 1;
            alu_op    = 4'b0000; // ADD for rs1 + imm
        end

        // ---------------------------
        // I-Type ALU
        // ---------------------------
        7'b0010011: begin
            reg_write = 1;
            alu_src   = 1;

            case (funct3)
                3'b000: alu_op = 4'b0000; // ADDI
                3'b010: alu_op = 4'b0101; // SLTI
                3'b011: alu_op = 4'b0110; // SLTIU
                3'b100: alu_op = 4'b0100; // XORI
                3'b110: alu_op = 4'b0011; // ORI
                3'b111: alu_op = 4'b0010; // ANDI
                3'b001: alu_op = 4'b0111; // SLLI
                3'b101: begin
                    if (funct7 == 7'b0000000)
                        alu_op = 4'b1000; // SRLI
                    else
                        alu_op = 4'b1001; // SRAI
                end
            endcase
        end

        // ---------------------------
        // LUI
        // ---------------------------
        7'b0110111: begin
            reg_write = 1;
            // ALU is not used
        end

        // ---------------------------
        // AUIPC
        // ---------------------------
        7'b0010111: begin
            reg_write = 1;
            // top-level ALU will compute PC + imm
        end

    endcase

end
endmodule

Single Pipelined/registers.v
module registers(
    input wire clk,
    input wire we,
    input wire [4:0] rs1_addr,
    input wire [4:0] rs2_addr,
    input wire [4:0] rd_addr,
    input wire [31:0] rd_data,
    output wire [31:0] rs1_data,
    output wire [31:0] rs2_data
);
    
    reg [31:0] regfile [0:31];

    // Read ports (combinational)
    assign rs1_data = (rs1_addr != 0) ? regfile[rs1_addr] : 32'd0;
    assign rs2_data = (rs2_addr != 0) ? regfile[rs2_addr] : 32'd0;

    // Write port (synchronous)
    always @(posedge clk) begin
        if (we && (rd_addr != 0)) begin
            regfile[rd_addr] <= rd_data;
        end
    end

    // Initialize registers to zero
    integer i;
    initial begin
        for (i = 0; i < 32; i = i + 1) begin
            regfile[i] = 32'd0;
        end
    end

endmodule

instr_decode.v
module instr_decode(
    input wire [31:0] instruction,
    output wire [6:0] opcode,
    output wire [4:0] rd,
    output wire [2:0] funct3,
    output wire [4:0] rs1,
    output wire [4:0] rs2,
    output wire [6:0] funct7,
    output reg [31:0] immediate
);

    // Field extraction using assign (combinational wires)
    assign opcode = instruction[6:0];
    assign rd     = instruction[11:7];
    assign funct3 = instruction[14:12];
    assign rs1    = instruction[19:15];
    assign rs2    = instruction[24:20];
    assign funct7 = instruction[31:25];
    
    // Immediate extraction (inside always block)
    always @(*) begin
        case (opcode)
            7'b0010011, // I-type ALU
            7'b0000011, // Loads
            7'b1100111: // JALR
                immediate = {{20{instruction[31]}}, instruction[31:20]};

            7'b0100011: // S-type
                immediate = {{20{instruction[31]}}, instruction[31:25], instruction[11:7]};

            7'b1100011: // B-type
                immediate = {{19{instruction[31]}}, instruction[31], instruction[7],
                              instruction[30:25], instruction[11:8], 1'b0};

            7'b1101111: // J-type (JAL)
                immediate = {{11{instruction[31]}}, instruction[31], instruction[19:12],
                             instruction[20], instruction[30:21], 1'b0};

            7'b0110111, // LUI (U-type)
            7'b0010111: // AUIPC
                immediate = {instruction[31:12], 12'b0};

            default:
                immediate = 32'd0;
        endcase
    end

endmodule

instruction_memory.v
module instr_mem(
    input wire [31:0] pc,
    output reg [31:0] instruction
);

    reg [31:0] memory [0:1023];

    initial begin
        $readmemh("instructions.hex", memory);
    end

    always @(*) begin
        instruction = memory[pc[11:2]];  // word address
    end

endmodule

programcounter.v
module programcounter(
    input wire clk,
    input wire reset,

    input wire branch_taken,
    input wire [31:0] branch_target,

    input wire jal, // Jump and Link pc = pc + immediate
    input wire jalr, // Jump and Link Register pc = rs1 + immediate
    input wire [31:0] jal_target,
    input wire [31:0] jalr_target,

    output reg [31:0] pc
);

reg [31:0] pc_next;

always @(*) begin
    // PC selection logic
    if (jalr)
        pc_next = jalr_target;
    else if (jal)
        pc_next = jal_target;
    else if (branch_taken)
        pc_next = branch_target;
    else
        pc_next = pc + 32'd4;
end

always @(posedge clk or posedge reset) begin
    if (reset)
        pc <= 32'd0;
    else
        pc <= pc_next;
end

endmodule

riscv-core.v
`timescale 1ns/1ps

module core(
    input  wire        clk,
    input  wire        reset,
    output wire [31:0] pc_out
);

    // PC / IF
    wire [31:0] pc;
    wire        branch_taken;
    wire [31:0] branch_target;
    wire        jal, jalr;
    wire [31:0] jal_target, jalr_target;

    assign pc_out = pc;

    programcounter pc_reg (
        .clk(clk),
        .reset(reset),
        .branch_taken(branch_taken),
        .branch_target(branch_target),
        .jal(jal),
        .jalr(jalr),
        .jal_target(jal_target),
        .jalr_target(jalr_target),
        .pc(pc)
    );

    // Instruction memory / fetch
    wire [31:0] instruction;

    instr_mem imem (
        .pc(pc),
        .instruction(instruction)
    );

    // Decode outputs
    wire [4:0]  rs1_addr;
    wire [4:0]  rs2_addr;
    wire [4:0]  rd_addr;
    wire [6:0]  opcode;
    wire [6:0]  funct7;
    wire [2:0]  funct3;
    wire [31:0] immediate;

    instr_decode id (
        .instruction(instruction),
        .opcode(opcode),
        .rd(rd_addr),
        .funct3(funct3),
        .rs1(rs1_addr),
        .rs2(rs2_addr),
        .funct7(funct7),
        .immediate(immediate)
    );

    // Register file
    wire [31:0] rs1_data;
    wire [31:0] rs2_data;

    // Write-back wires
    wire        reg_write;
    wire [31:0] wb_data;
    wire        mem_to_reg;

    registers regs (
        .clk(clk),
        .we(reg_write),
        .rs1_addr(rs1_addr),
        .rs2_addr(rs2_addr),
        .rd_addr(rd_addr),
        .rd_data(wb_data),
        .rs1_data(rs1_data),
        .rs2_data(rs2_data)
    );

    // Control signals
    wire        branch;
    wire        mem_read;
    wire        mem_write;
    wire        alu_src;
    wire [3:0]  alu_op;
    // mem_to_reg declared earlier as wire; comes from control unit

    control_unit cu (
        .opcode(opcode),
        .funct3(funct3),
        .funct7(funct7),
        .alu_op(alu_op),
        .alu_src(alu_src),
        .mem_to_reg(mem_to_reg),
        .reg_write(reg_write),
        .mem_read(mem_read),
        .mem_write(mem_write),
        .branch(branch),
        .jal(jal),
        .jalr(jalr)
    );

    // ALU inputs (AUIPC / LUI support)
    wire is_auipc = (opcode == 7'b0010111);
    wire is_lui   = (opcode == 7'b0110111);

    wire [31:0] alu_a = (is_auipc) ? pc : rs1_data;      // AUIPC uses PC + imm
    wire [31:0] alu_b = (alu_src) ? immediate : rs2_data;

    wire [31:0] alu_result;
    wire        alu_zero;

    ALU alu_unit (
        .a(alu_a),
        .b(alu_b),
        .alu_op(alu_op),
        .result(alu_result),
        .zero(alu_zero)
    );

    // Branch unit (pass register values, not addresses)
    branch_unit bu (
        .branch(branch),
        .rs1(rs1_data),
        .rs2(rs2_data),
        .funct3(funct3),
        .branch_taken(branch_taken)
    );

    // Branch and Jump target calculation (use immediate produced by decode)
    assign branch_target = pc + immediate;                       // B-type imm expected
    assign jal_target    = pc + immediate;                       // J-type imm expected
    assign jalr_target   = (rs1_data + immediate) & 32'hfffffffe; // JALR: rs1 + imm, LSB=0

    // Data memory
    wire [31:0] mem_read_data;

    data_mem dmem (
        .clk(clk),
        .mem_read(mem_read),
        .mem_write(mem_write),
        .funct3(funct3),
        .address(alu_result),
        .write_data(rs2_data),
        .read_data(mem_read_data)
    );

    // Writeback selection
    wire [31:0] pc_plus4 = pc + 32'd4;
    wire [31:0] lui_value = immediate; // decode must supply U-type immediate as {inst[31:12],12'b0}

    assign wb_data = (reg_write && (jal || jalr)) ? pc_plus4 :
                     (reg_write && is_lui)              ? lui_value :
                     (reg_write && mem_to_reg)          ? mem_read_data :
                     (reg_write)                        ? alu_result :
                                                          32'd0;

endmodule

total_tb.v
`timescale 1ns/1ps

module tb_core_sum;

    reg clk;
    reg reset;

    wire [31:0] pc_out;

    // Instantiate your core
    core uut (
        .clk(clk),
        .reset(reset),
        .pc_out(pc_out)
    );

    // Generate clock (10ns period)
    always #5 clk = ~clk;

    integer cycle;

    initial begin
        $display("=== RV32I CORE: SUM OF FIRST 10 NATURAL NUMBERS ===");
        
        clk = 0;
        reset = 1;

        // Enable wave dump
        $dumpfile("core.vcd");
        $dumpvars(0, tb_core_sum);

        // Hold reset for a few cycles
        #20;
        reset = 0;

        // Run for 50 cycles
        for (cycle = 0; cycle < 50; cycle = cycle + 1) begin
            @(posedge clk);

            // Print PC + registers x10(sum), x11(i), x12(limit)
            $display("Cycle %0d | PC=%h | x10(sum)=%h | x11(i)=%h | x12(limit)=%h",
                cycle,
                pc_out,
                uut.regs.regfile[10],
                uut.regs.regfile[11],
                uut.regs.regfile[12]
            );
        end

        $display("=== SIMULATION COMPLETE ===");
        $finish;
    end

endmodule

core.vcd
$date
	Sat Nov 15 20:59:33 2025
$end
$version
	Icarus Verilog
$end
$timescale
	1ps
$end
$scope module tb_core_sum $end
$var wire 32 ! pc_out [31:0] $end
$var reg 1 " clk $end
$var integer 32 # cycle [31:0] $end
$var reg 1 $ reset $end
$scope module uut $end
$var wire 32 % alu_a [31:0] $end
$var wire 32 & alu_b [31:0] $end
$var wire 4 ' alu_op [3:0] $end
$var wire 32 ( alu_result [31:0] $end
$var wire 1 ) alu_src $end
$var wire 1 * alu_zero $end
$var wire 1 + branch $end
$var wire 1 , branch_taken $end
$var wire 32 - branch_target [31:0] $end
$var wire 1 . clk $end
$var wire 3 / funct3 [2:0] $end
$var wire 7 0 funct7 [6:0] $end
$var wire 32 1 immediate [31:0] $end
$var wire 32 2 instruction [31:0] $end
$var wire 1 3 is_auipc $end
$var wire 1 4 is_lui $end
$var wire 1 5 jal $end
$var wire 32 6 jal_target [31:0] $end
$var wire 1 7 jalr $end
$var wire 32 8 jalr_target [31:0] $end
$var wire 32 9 lui_value [31:0] $end
$var wire 1 : mem_read $end
$var wire 32 ; mem_read_data [31:0] $end
$var wire 1 < mem_to_reg $end
$var wire 1 = mem_write $end
$var wire 7 > opcode [6:0] $end
$var wire 32 ? pc [31:0] $end
$var wire 32 @ pc_out [31:0] $end
$var wire 32 A pc_plus4 [31:0] $end
$var wire 5 B rd_addr [4:0] $end
$var wire 1 C reg_write $end
$var wire 1 D reset $end
$var wire 5 E rs1_addr [4:0] $end
$var wire 32 F rs1_data [31:0] $end
$var wire 5 G rs2_addr [4:0] $end
$var wire 32 H rs2_data [31:0] $end
$var wire 32 I wb_data [31:0] $end
$scope module pc_reg $end
$var wire 1 , branch_taken $end
$var wire 32 J branch_target [31:0] $end
$var wire 1 . clk $end
$var wire 1 5 jal $end
$var wire 32 K jal_target [31:0] $end
$var wire 1 7 jalr $end
$var wire 32 L jalr_target [31:0] $end
$var wire 1 D reset $end
$var reg 32 M pc [31:0] $end
$var reg 32 N pc_next [31:0] $end
$upscope $end
$scope module imem $end
$var wire 32 O pc [31:0] $end
$var reg 32 P instruction [31:0] $end
$upscope $end
$scope module id $end
$var wire 3 Q funct3 [2:0] $end
$var wire 7 R funct7 [6:0] $end
$var wire 32 S instruction [31:0] $end
$var wire 7 T opcode [6:0] $end
$var wire 5 U rd [4:0] $end
$var wire 5 V rs1 [4:0] $end
$var wire 5 W rs2 [4:0] $end
$var reg 32 X immediate [31:0] $end
$upscope $end
$scope module regs $end
$var wire 1 . clk $end
$var wire 5 Y rd_addr [4:0] $end
$var wire 32 Z rd_data [31:0] $end
$var wire 5 [ rs1_addr [4:0] $end
$var wire 32 \ rs1_data [31:0] $end
$var wire 5 ] rs2_addr [4:0] $end
$var wire 32 ^ rs2_data [31:0] $end
$var wire 1 C we $end
$var integer 32 _ i [31:0] $end
$upscope $end
$scope module cu $end
$var wire 3 ` funct3 [2:0] $end
$var wire 7 a funct7 [6:0] $end
$var wire 7 b opcode [6:0] $end
$var reg 4 c alu_op [3:0] $end
$var reg 1 d alu_src $end
$var reg 1 e branch $end
$var reg 1 f jal $end
$var reg 1 g jalr $end
$var reg 1 h mem_read $end
$var reg 1 i mem_to_reg $end
$var reg 1 j mem_write $end
$var reg 1 k reg_write $end
$upscope $end
$scope module alu_unit $end
$var wire 32 l a [31:0] $end
$var wire 4 m alu_op [3:0] $end
$var wire 32 n b [31:0] $end
$var reg 32 o result [31:0] $end
$var reg 1 p zero $end
$upscope $end
$scope module bu $end
$var wire 1 + branch $end
$var wire 3 q funct3 [2:0] $end
$var wire 32 r rs1 [31:0] $end
$var wire 32 s rs2 [31:0] $end
$var reg 1 t branch_taken $end
$upscope $end
$scope module dmem $end
$var wire 12 u addr [11:0] $end
$var wire 32 v address [31:0] $end
$var wire 1 . clk $end
$var wire 3 w funct3 [2:0] $end
$var wire 1 : mem_read $end
$var wire 1 = mem_write $end
$var wire 32 x write_data [31:0] $end
$var reg 32 y read_data [31:0] $end
$upscope $end
$upscope $end
$upscope $end
$enddefinitions $end
#0
$dumpvars
b0 y
b0 x
b0 w
b0 v
b0 u
0t
b0 s
b0 r
b0 q
1p
b0 o
b0 n
b0 m
b0 l
1k
0j
0i
0h
0g
0f
0e
1d
b0 c
b10011 b
b0 a
b0 `
b100000 _
b0 ^
b0 ]
b0 \
b0 [
b0 Z
b1010 Y
b0 X
b0 W
b0 V
b1010 U
b10011 T
b10100010011 S
b0 R
b0 Q
b10100010011 P
b0 O
b100 N
b0 M
b0 L
b0 K
b0 J
b0 I
b0 H
b0 G
b0 F
b0 E
1D
1C
b1010 B
b100 A
b0 @
b0 ?
b10011 >
0=
0<
b0 ;
0:
b0 9
b0 8
07
b0 6
05
04
03
b10100010011 2
b0 1
b0 0
b0 /
0.
b0 -
0,
0+
1*
1)
b0 (
b0 '
b0 &
b0 %
1$
bx #
0"
b0 !
$end
#5000
1"
1.
#10000
0"
0.
#15000
1"
1.
#20000
0"
0.
b0 #
0$
0D
#25000
b1 I
b1 Z
b1 u
0p
0*
b1 o
b1 (
b1 v
b1 &
b1 n
b1011 B
b1011 U
b1011 Y
b1 G
b1 W
b1 ]
b1 X
b1 1
b1 9
b100000000010110010011 P
b100000000010110010011 2
b100000000010110010011 S
b1000 N
b100 M
b1000 A
b101 6
b101 K
b101 -
b101 J
b100 ?
b100 O
b100 !
b100 @
b1 #
1"
1.
#30000
0"
0.
#35000
b1011 I
b1011 Z
b1011 u
b1011 o
b1011 (
b1011 v
b1 H
b1 ^
b1 s
b1 x
b1010 8
b1010 L
b1011 &
b1011 n
b1100 B
b1100 U
b1100 Y
b1011 G
b1011 W
b1011 ]
b1011 X
b1011 1
b1011 9
b101100000000011000010011 P
b101100000000011000010011 2
b101100000000011000010011 S
b1100 N
b1000 M
b1100 A
b10011 6
b10011 K
b10011 -
b10011 J
b1000 ?
b1000 O
b1000 !
b1000 @
b10 #
1"
1.
#40000
0"
0.
#45000
b1 I
b1 Z
b1 u
b1 o
b1 (
b1 v
b0 8
b0 L
b1 &
b1 n
1k
1C
0d
0)
b0 X
b0 1
b0 9
b110011 >
b110011 T
b110011 b
b1010 B
b1010 U
b1010 Y
b1010 E
b1010 V
b1010 [
b101101010000010100110011 P
b101101010000010100110011 2
b101101010000010100110011 S
b10000 N
b1100 M
b10000 A
b1100 6
b1100 K
b1100 -
b1100 J
b1100 ?
b1100 O
b1100 !
b1100 @
b11 #
1"
1.
#50000
0"
0.
#55000
b10 I
b10 Z
b10 u
b10 8
b10 L
b10 o
b10 (
b10 v
1d
1)
1k
1C
b1 X
b1 1
b1 9
b0 H
b0 ^
b0 s
b0 x
b1 %
b1 l
b10011 >
b10011 T
b10011 b
b1011 B
b1011 U
b1011 Y
b1011 E
b1011 V
b1011 [
b1 G
b1 W
b1 ]
b1 F
b1 \
b1 r
b101011000010110010011 P
b101011000010110010011 2
b101011000010110010011 S
b10100 N
b10000 M
b10100 A
b10001 6
b10001 K
b10001 -
b10001 J
b10000 ?
b10000 O
b10000 !
b10000 @
b100 #
1"
1.
#60000
0"
0.
#65000
b0 I
b0 Z
b111111110111 u
1t
1,
b11111111111111111111111111110111 o
b11111111111111111111111111110111 (
b11111111111111111111111111110111 v
b1011 H
b1011 ^
b1011 s
b1011 x
b1 c
b1 '
b1 m
1e
1+
0k
0C
0d
0)
b1011 &
b1011 n
b11111111111111111111111111111010 8
b11111111111111111111111111111010 L
b10 %
b10 l
b1100011 >
b1100011 T
b1100011 b
b11001 B
b11001 U
b11001 Y
b100 /
b100 Q
b100 `
b100 q
b100 w
b1100 G
b1100 W
b1100 ]
b1111111 0
b1111111 R
b1111111 a
b11111111111111111111111111111000 X
b11111111111111111111111111111000 1
b11111111111111111111111111111000 9
b10 F
b10 \
b10 r
b11111110110001011100110011100011 P
b11111110110001011100110011100011 2
b11111110110001011100110011100011 S
b1100 N
b10100 M
b11000 A
b1100 6
b1100 K
b1100 -
b1100 J
b10100 ?
b10100 O
b10100 !
b10100 @
b101 #
1"
1.
#70000
0"
0.
#75000
b11 I
b11 Z
b11 u
b1 %
b1 l
b10 &
b10 n
b11 o
b11 (
b11 v
0t
0,
b1 F
b1 \
b1 r
b10 H
b10 ^
b10 s
b10 x
1k
1C
b0 c
b0 '
b0 m
0e
0+
b0 8
b0 L
b110011 >
b110011 T
b110011 b
b1010 B
b1010 U
b1010 Y
b0 /
b0 Q
b0 `
b0 q
b0 w
b1010 E
b1010 V
b1010 [
b1011 G
b1011 W
b1011 ]
b0 0
b0 R
b0 a
b0 X
b0 1
b0 9
b101101010000010100110011 P
b101101010000010100110011 2
b101101010000010100110011 S
b10000 N
b1100 M
b10000 A
b1100 6
b1100 K
b1100 -
b1100 J
b1100 ?
b1100 O
b1100 !
b1100 @
b110 #
1"
1.
#80000
0"
0.
#85000
b11 I
b11 Z
b11 u
b1 &
b1 n
b11 o
b11 (
b11 v
1d
1)
1k
1C
b1 X
b1 1
b1 9
b0 H
b0 ^
b0 s
b0 x
b10 8
b10 L
b10 %
b10 l
b10011 >
b10011 T
b10011 b
b1011 B
b1011 U
b1011 Y
b1011 E
b1011 V
b1011 [
b1 G
b1 W
b1 ]
b10 F
b10 \
b10 r
b101011000010110010011 P
b101011000010110010011 2
b101011000010110010011 S
b10100 N
b10000 M
b10100 A
b10001 6
b10001 K
b10001 -
b10001 J
b10000 ?
b10000 O
b10000 !
b10000 @
b111 #
1"
1.
#90000
0"
0.
#95000
b0 I
b0 Z
b111111111000 u
1t
1,
b11111111111111111111111111111000 o
b11111111111111111111111111111000 (
b11111111111111111111111111111000 v
b1011 H
b1011 ^
b1011 s
b1011 x
b1 c
b1 '
b1 m
1e
1+
0k
0C
0d
0)
b1011 &
b1011 n
b11111111111111111111111111111010 8
b11111111111111111111111111111010 L
b11 %
b11 l
b1100011 >
b1100011 T
b1100011 b
b11001 B
b11001 U
b11001 Y
b100 /
b100 Q
b100 `
b100 q
b100 w
b1100 G
b1100 W
b1100 ]
b1111111 0
b1111111 R
b1111111 a
b11111111111111111111111111111000 X
b11111111111111111111111111111000 1
b11111111111111111111111111111000 9
b11 F
b11 \
b11 r
b11111110110001011100110011100011 P
b11111110110001011100110011100011 2
b11111110110001011100110011100011 S
b1100 N
b10100 M
b11000 A
b1100 6
b1100 K
b1100 -
b1100 J
b10100 ?
b10100 O
b10100 !
b10100 @
b1000 #
1"
1.
#100000
0"
0.
#105000
b110 I
b110 Z
b110 u
b11 &
b11 n
b110 o
b110 (
b110 v
0t
0,
b11 H
b11 ^
b11 s
b11 x
1k
1C
b0 c
b0 '
b0 m
0e
0+
b10 8
b10 L
b110011 >
b110011 T
b110011 b
b1010 B
b1010 U
b1010 Y
b0 /
b0 Q
b0 `
b0 q
b0 w
b1010 E
b1010 V
b1010 [
b1011 G
b1011 W
b1011 ]
b0 0
b0 R
b0 a
b0 X
b0 1
b0 9
b101101010000010100110011 P
b101101010000010100110011 2
b101101010000010100110011 S
b10000 N
b1100 M
b10000 A
b1100 6
b1100 K
b1100 -
b1100 J
b1100 ?
b1100 O
b1100 !
b1100 @
b1001 #
1"
1.
#110000
0"
0.
#115000
b100 I
b100 Z
b100 u
b1 &
b1 n
b100 o
b100 (
b100 v
1d
1)
1k
1C
b1 X
b1 1
b1 9
b0 H
b0 ^
b0 s
b0 x
b100 8
b100 L
b11 %
b11 l
b10011 >
b10011 T
b10011 b
b1011 B
b1011 U
b1011 Y
b1011 E
b1011 V
b1011 [
b1 G
b1 W
b1 ]
b11 F
b11 \
b11 r
b101011000010110010011 P
b101011000010110010011 2
b101011000010110010011 S
b10100 N
b10000 M
b10100 A
b10001 6
b10001 K
b10001 -
b10001 J
b10000 ?
b10000 O
b10000 !
b10000 @
b1010 #
1"
1.
#120000
0"
0.
#125000
b0 I
b0 Z
b111111111001 u
1t
1,
b11111111111111111111111111111001 o
b11111111111111111111111111111001 (
b11111111111111111111111111111001 v
b1011 H
b1011 ^
b1011 s
b1011 x
b1 c
b1 '
b1 m
1e
1+
0k
0C
0d
0)
b1011 &
b1011 n
b11111111111111111111111111111100 8
b11111111111111111111111111111100 L
b100 %
b100 l
b1100011 >
b1100011 T
b1100011 b
b11001 B
b11001 U
b11001 Y
b100 /
b100 Q
b100 `
b100 q
b100 w
b1100 G
b1100 W
b1100 ]
b1111111 0
b1111111 R
b1111111 a
b11111111111111111111111111111000 X
b11111111111111111111111111111000 1
b11111111111111111111111111111000 9
b100 F
b100 \
b100 r
b11111110110001011100110011100011 P
b11111110110001011100110011100011 2
b11111110110001011100110011100011 S
b1100 N
b10100 M
b11000 A
b1100 6
b1100 K
b1100 -
b1100 J
b10100 ?
b10100 O
b10100 !
b10100 @
b1011 #
1"
1.
#130000
0"
0.
#135000
b1010 I
b1010 Z
b1010 u
b110 %
b110 l
b100 &
b100 n
b1010 o
b1010 (
b1010 v
0t
0,
b110 F
b110 \
b110 r
b100 H
b100 ^
b100 s
b100 x
1k
1C
b0 c
b0 '
b0 m
0e
0+
b110 8
b110 L
b110011 >
b110011 T
b110011 b
b1010 B
b1010 U
b1010 Y
b0 /
b0 Q
b0 `
b0 q
b0 w
b1010 E
b1010 V
b1010 [
b1011 G
b1011 W
b1011 ]
b0 0
b0 R
b0 a
b0 X
b0 1
b0 9
b101101010000010100110011 P
b101101010000010100110011 2
b101101010000010100110011 S
b10000 N
b1100 M
b10000 A
b1100 6
b1100 K
b1100 -
b1100 J
b1100 ?
b1100 O
b1100 !
b1100 @
b1100 #
1"
1.
#140000
0"
0.
#145000
b101 I
b101 Z
b101 u
b1 &
b1 n
b101 o
b101 (
b101 v
1d
1)
1k
1C
b1 X
b1 1
b1 9
b0 H
b0 ^
b0 s
b0 x
b100 8
b100 L
b100 %
b100 l
b10011 >
b10011 T
b10011 b
b1011 B
b1011 U
b1011 Y
b1011 E
b1011 V
b1011 [
b1 G
b1 W
b1 ]
b100 F
b100 \
b100 r
b101011000010110010011 P
b101011000010110010011 2
b101011000010110010011 S
b10100 N
b10000 M
b10100 A
b10001 6
b10001 K
b10001 -
b10001 J
b10000 ?
b10000 O
b10000 !
b10000 @
b1101 #
1"
1.
#150000
0"
0.
#155000
b0 I
b0 Z
b111111111010 u
1t
1,
b11111111111111111111111111111010 o
b11111111111111111111111111111010 (
b11111111111111111111111111111010 v
b1011 H
b1011 ^
b1011 s
b1011 x
b1 c
b1 '
b1 m
1e
1+
0k
0C
0d
0)
b1011 &
b1011 n
b11111111111111111111111111111100 8
b11111111111111111111111111111100 L
b101 %
b101 l
b1100011 >
b1100011 T
b1100011 b
b11001 B
b11001 U
b11001 Y
b100 /
b100 Q
b100 `
b100 q
b100 w
b1100 G
b1100 W
b1100 ]
b1111111 0
b1111111 R
b1111111 a
b11111111111111111111111111111000 X
b11111111111111111111111111111000 1
b11111111111111111111111111111000 9
b101 F
b101 \
b101 r
b11111110110001011100110011100011 P
b11111110110001011100110011100011 2
b11111110110001011100110011100011 S
b1100 N
b10100 M
b11000 A
b1100 6
b1100 K
b1100 -
b1100 J
b10100 ?
b10100 O
b10100 !
b10100 @
b1110 #
1"
1.
#160000
0"
0.
#165000
b1111 I
b1111 Z
b1111 u
b1010 %
b1010 l
b101 &
b101 n
b1111 o
b1111 (
b1111 v
0t
0,
b1010 F
b1010 \
b1010 r
b101 H
b101 ^
b101 s
b101 x
1k
1C
b0 c
b0 '
b0 m
0e
0+
b1010 8
b1010 L
b110011 >
b110011 T
b110011 b
b1010 B
b1010 U
b1010 Y
b0 /
b0 Q
b0 `
b0 q
b0 w
b1010 E
b1010 V
b1010 [
b1011 G
b1011 W
b1011 ]
b0 0
b0 R
b0 a
b0 X
b0 1
b0 9
b101101010000010100110011 P
b101101010000010100110011 2
b101101010000010100110011 S
b10000 N
b1100 M
b10000 A
b1100 6
b1100 K
b1100 -
b1100 J
b1100 ?
b1100 O
b1100 !
b1100 @
b1111 #
1"
1.
#170000
0"
0.
#175000
b110 I
b110 Z
b110 u
b1 &
b1 n
b110 o
b110 (
b110 v
1d
1)
1k
1C
b1 X
b1 1
b1 9
b0 H
b0 ^
b0 s
b0 x
b110 8
b110 L
b101 %
b101 l
b10011 >
b10011 T
b10011 b
b1011 B
b1011 U
b1011 Y
b1011 E
b1011 V
b1011 [
b1 G
b1 W
b1 ]
b101 F
b101 \
b101 r
b101011000010110010011 P
b101011000010110010011 2
b101011000010110010011 S
b10100 N
b10000 M
b10100 A
b10001 6
b10001 K
b10001 -
b10001 J
b10000 ?
b10000 O
b10000 !
b10000 @
b10000 #
1"
1.
#180000
0"
0.
